{
    "/tenant/js/app.js": "/tenant/js/app.js",
    "/js/app.js": "/js/app.js",
    "/tenant/css/app.css": "/tenant/css/app.css",
    "/js/app-landing.js": "/js/app-landing.js",
    "/css/all.css": "/css/all.css",
    "/css/all-landing.css": "/css/all-landing.css",
    "/img/app-bg.png": "/img/app-bg.png",
    "/img/arrow1.png": "/img/arrow1.png",
    "/img/arrow2.png": "/img/arrow2.png",
    "/img/intro01.png": "/img/intro01.png",
    "/img/intro02.png": "/img/intro02.png",
    "/img/intro03.png": "/img/intro03.png",
    "/img/item-01.png": "/img/item-01.png",
    "/img/item-02.png": "/img/item-02.png",
    "/img/mobile.png": "/img/mobile.png",
    "/fonts/fontawesome-webfont.eot": "/fonts/fontawesome-webfont.eot",
    "/fonts/fontawesome-webfont.svg": "/fonts/fontawesome-webfont.svg",
    "/fonts/fontawesome-webfont.ttf": "/fonts/fontawesome-webfont.ttf",
    "/fonts/fontawesome-webfont.woff": "/fonts/fontawesome-webfont.woff",
    "/fonts/fontawesome-webfont.woff2": "/fonts/fontawesome-webfont.woff2",
    "/fonts/FontAwesome.otf": "/fonts/FontAwesome.otf",
    "/fonts/ionicons.eot": "/fonts/ionicons.eot",
    "/fonts/ionicons.svg": "/fonts/ionicons.svg",
    "/fonts/ionicons.ttf": "/fonts/ionicons.ttf",
    "/fonts/ionicons.woff": "/fonts/ionicons.woff",
    "/fonts/ionicons.woff2": "/fonts/ionicons.woff2",
    "/fonts/glyphicons-halflings-regular.eot": "/fonts/glyphicons-halflings-regular.eot",
    "/fonts/glyphicons-halflings-regular.svg": "/fonts/glyphicons-halflings-regular.svg",
    "/fonts/glyphicons-halflings-regular.ttf": "/fonts/glyphicons-halflings-regular.ttf",
    "/fonts/glyphicons-halflings-regular.woff": "/fonts/glyphicons-halflings-regular.woff",
    "/fonts/glyphicons-halflings-regular.woff2": "/fonts/glyphicons-halflings-regular.woff2",
    "/css/skins/_all-skins.css": "/css/skins/_all-skins.css",
    "/css/skins/_all-skins.min.css": "/css/skins/_all-skins.min.css",
    "/css/skins/skin-black-light.css": "/css/skins/skin-black-light.css",
    "/css/skins/skin-black-light.min.css": "/css/skins/skin-black-light.min.css",
    "/css/skins/skin-black.css": "/css/skins/skin-black.css",
    "/css/skins/skin-black.min.css": "/css/skins/skin-black.min.css",
    "/css/skins/skin-blue-light.css": "/css/skins/skin-blue-light.css",
    "/css/skins/skin-blue-light.min.css": "/css/skins/skin-blue-light.min.css",
    "/css/skins/skin-blue.css": "/css/skins/skin-blue.css",
    "/css/skins/skin-blue.min.css": "/css/skins/skin-blue.min.css",
    "/css/skins/skin-green-light.css": "/css/skins/skin-green-light.css",
    "/css/skins/skin-green-light.min.css": "/css/skins/skin-green-light.min.css",
    "/css/skins/skin-green.css": "/css/skins/skin-green.css",
    "/css/skins/skin-green.min.css": "/css/skins/skin-green.min.css",
    "/css/skins/skin-purple-light.css": "/css/skins/skin-purple-light.css",
    "/css/skins/skin-purple-light.min.css": "/css/skins/skin-purple-light.min.css",
    "/css/skins/skin-purple.css": "/css/skins/skin-purple.css",
    "/css/skins/skin-purple.min.css": "/css/skins/skin-purple.min.css",
    "/css/skins/skin-red-light.css": "/css/skins/skin-red-light.css",
    "/css/skins/skin-red-light.min.css": "/css/skins/skin-red-light.min.css",
    "/css/skins/skin-red.css": "/css/skins/skin-red.css",
    "/css/skins/skin-red.min.css": "/css/skins/skin-red.min.css",
    "/css/skins/skin-yellow-light.css": "/css/skins/skin-yellow-light.css",
    "/css/skins/skin-yellow-light.min.css": "/css/skins/skin-yellow-light.min.css",
    "/css/skins/skin-yellow.css": "/css/skins/skin-yellow.css",
    "/css/skins/skin-yellow.min.css": "/css/skins/skin-yellow.min.css",
    "/css/blue.png": "/css/blue.png",
    "/css/blue@2x.png": "/css/blue@2x.png",
    "/0.b850d2fe499135c86e9c.hot-update.js": "/0.b850d2fe499135c86e9c.hot-update.js",
    "/0.6f5e75f2c5a742c64674.hot-update.js": "/0.6f5e75f2c5a742c64674.hot-update.js",
    "/0.ea277ca099beeb2d12e7.hot-update.js": "/0.ea277ca099beeb2d12e7.hot-update.js",
    "/0.ad26a54748e21abde0b4.hot-update.js": "/0.ad26a54748e21abde0b4.hot-update.js",
    "/0.04716bc23240b368c686.hot-update.js": "/0.04716bc23240b368c686.hot-update.js",
    "/0.e75c01bc97f404177048.hot-update.js": "/0.e75c01bc97f404177048.hot-update.js",
    "/0.d5417d71943ee5cc9b35.hot-update.js": "/0.d5417d71943ee5cc9b35.hot-update.js",
    "/0.a699abf683cfae47819f.hot-update.js": "/0.a699abf683cfae47819f.hot-update.js",
    "/0.5821e0c791166058722c.hot-update.js": "/0.5821e0c791166058722c.hot-update.js",
    "/0.9d59184483bfd2d145e0.hot-update.js": "/0.9d59184483bfd2d145e0.hot-update.js",
    "/0.44012c0eb8b0650b9a44.hot-update.js": "/0.44012c0eb8b0650b9a44.hot-update.js",
    "/0.ea9fa2892f24a70286d4.hot-update.js": "/0.ea9fa2892f24a70286d4.hot-update.js",
    "/0.1b247107773da6853263.hot-update.js": "/0.1b247107773da6853263.hot-update.js",
    "/0.68cdf530c75cbea4fc8a.hot-update.js": "/0.68cdf530c75cbea4fc8a.hot-update.js",
    "/0.80a7df323d0bff07440f.hot-update.js": "/0.80a7df323d0bff07440f.hot-update.js",
    "/0.ce38ed7a4470d611adf5.hot-update.js": "/0.ce38ed7a4470d611adf5.hot-update.js",
    "/0.107f64b3143887c3ab8b.hot-update.js": "/0.107f64b3143887c3ab8b.hot-update.js",
    "/0.acd3900967309fd4be35.hot-update.js": "/0.acd3900967309fd4be35.hot-update.js",
    "/0.96ae80d482841e5dbb72.hot-update.js": "/0.96ae80d482841e5dbb72.hot-update.js",
    "/0.c0893b1bffc642dab14f.hot-update.js": "/0.c0893b1bffc642dab14f.hot-update.js",
    "/0.782c7193cef678817288.hot-update.js": "/0.782c7193cef678817288.hot-update.js",
    "/0.99806f7a529fd26e03f8.hot-update.js": "/0.99806f7a529fd26e03f8.hot-update.js",
    "/0.de8797936f4ba0fe0deb.hot-update.js": "/0.de8797936f4ba0fe0deb.hot-update.js",
    "/0.4b2f2c1048a1d8dc5f96.hot-update.js": "/0.4b2f2c1048a1d8dc5f96.hot-update.js",
    "/0.b4df9659d4f34d20fb21.hot-update.js": "/0.b4df9659d4f34d20fb21.hot-update.js",
    "/0.caa8e660884cbcd5a172.hot-update.js": "/0.caa8e660884cbcd5a172.hot-update.js",
    "/0.cea98de76a3c5fafc840.hot-update.js": "/0.cea98de76a3c5fafc840.hot-update.js",
    "/0.2b8fef5b82c587c73f41.hot-update.js": "/0.2b8fef5b82c587c73f41.hot-update.js",
    "/0.624b12a6ce06ccff6327.hot-update.js": "/0.624b12a6ce06ccff6327.hot-update.js",
    "/0.4f9dea123a539e60de11.hot-update.js": "/0.4f9dea123a539e60de11.hot-update.js",
    "/0.def2fafb652f32de3dd5.hot-update.js": "/0.def2fafb652f32de3dd5.hot-update.js",
    "/0.d27b78dc842a4cf2f286.hot-update.js": "/0.d27b78dc842a4cf2f286.hot-update.js",
    "/0.6dccb6dabb7b4252dcc4.hot-update.js": "/0.6dccb6dabb7b4252dcc4.hot-update.js",
    "/0.90d15525e150b62bc35f.hot-update.js": "/0.90d15525e150b62bc35f.hot-update.js",
    "/0.f1ae0274dfc0b83a3858.hot-update.js": "/0.f1ae0274dfc0b83a3858.hot-update.js",
    "/0.8b6b9cb1e3db48643892.hot-update.js": "/0.8b6b9cb1e3db48643892.hot-update.js",
    "/0.57bca4794578f38ae0a4.hot-update.js": "/0.57bca4794578f38ae0a4.hot-update.js",
    "/0.550b07ce0cb7f62017ca.hot-update.js": "/0.550b07ce0cb7f62017ca.hot-update.js",
    "/0.fc5e0365503f8e75b2ac.hot-update.js": "/0.fc5e0365503f8e75b2ac.hot-update.js",
    "/0.ab7b3237a6f29c65bba2.hot-update.js": "/0.ab7b3237a6f29c65bba2.hot-update.js",
    "/0.249860e17d116405341f.hot-update.js": "/0.249860e17d116405341f.hot-update.js",
    "/0.5549198eb35b30ee51bc.hot-update.js": "/0.5549198eb35b30ee51bc.hot-update.js",
    "/0.3f16b6c09df222147aa9.hot-update.js": "/0.3f16b6c09df222147aa9.hot-update.js",
    "/0.f38835bba5097038a1df.hot-update.js": "/0.f38835bba5097038a1df.hot-update.js",
    "/0.b0a3c8b36349aa3105da.hot-update.js": "/0.b0a3c8b36349aa3105da.hot-update.js",
    "/0.620993a1beada9b62b1d.hot-update.js": "/0.620993a1beada9b62b1d.hot-update.js",
    "/0.44323b5375e0316de36b.hot-update.js": "/0.44323b5375e0316de36b.hot-update.js",
    "/0.06850ed0175113693bdd.hot-update.js": "/0.06850ed0175113693bdd.hot-update.js",
    "/0.28c26e42c0061572fcaf.hot-update.js": "/0.28c26e42c0061572fcaf.hot-update.js",
    "/0.5d151f6727fd45451cec.hot-update.js": "/0.5d151f6727fd45451cec.hot-update.js",
    "/0.9c25aac14277739104ad.hot-update.js": "/0.9c25aac14277739104ad.hot-update.js",
    "/0.eab61a2e8a38d705cbf0.hot-update.js": "/0.eab61a2e8a38d705cbf0.hot-update.js",
    "/0.3861b3b9a5f542468adf.hot-update.js": "/0.3861b3b9a5f542468adf.hot-update.js",
    "/0.76b7ed89b907f15af071.hot-update.js": "/0.76b7ed89b907f15af071.hot-update.js",
    "/0.f72054e951a5198abeef.hot-update.js": "/0.f72054e951a5198abeef.hot-update.js",
    "/0.4a8d2d87703dc0e37647.hot-update.js": "/0.4a8d2d87703dc0e37647.hot-update.js",
    "/0.ff671eeaea14702291e0.hot-update.js": "/0.ff671eeaea14702291e0.hot-update.js",
    "/0.c12bcce01246f75bb895.hot-update.js": "/0.c12bcce01246f75bb895.hot-update.js",
    "/0.6c4c86cd2d4c66e170d3.hot-update.js": "/0.6c4c86cd2d4c66e170d3.hot-update.js",
    "/0.33f56e4c3c183455c4da.hot-update.js": "/0.33f56e4c3c183455c4da.hot-update.js",
    "/0.17b693e47aa758ee3ba5.hot-update.js": "/0.17b693e47aa758ee3ba5.hot-update.js",
    "/0.1de1afbcc666ecc8b326.hot-update.js": "/0.1de1afbcc666ecc8b326.hot-update.js",
    "/0.1b6cdac5e1a15164878f.hot-update.js": "/0.1b6cdac5e1a15164878f.hot-update.js",
    "/0.f3f0fe0e090e6071ba55.hot-update.js": "/0.f3f0fe0e090e6071ba55.hot-update.js",
    "/0.b1c1a5ed1971f3d3f4f4.hot-update.js": "/0.b1c1a5ed1971f3d3f4f4.hot-update.js",
    "/0.cd757df7219bd1cac7a4.hot-update.js": "/0.cd757df7219bd1cac7a4.hot-update.js",
    "/0.a3301c8f483f1c1d5d99.hot-update.js": "/0.a3301c8f483f1c1d5d99.hot-update.js",
    "/0.4ab71a8f8808fe1f75c1.hot-update.js": "/0.4ab71a8f8808fe1f75c1.hot-update.js",
    "/0.b7c658b786f2bcf8bac0.hot-update.js": "/0.b7c658b786f2bcf8bac0.hot-update.js",
    "/0.1b178220397e18d68f5b.hot-update.js": "/0.1b178220397e18d68f5b.hot-update.js",
    "/0.81d8bf96c55e4e1e1162.hot-update.js": "/0.81d8bf96c55e4e1e1162.hot-update.js",
    "/0.5ad359eb16a760724a29.hot-update.js": "/0.5ad359eb16a760724a29.hot-update.js",
    "/0.d00ebef73a704d897afa.hot-update.js": "/0.d00ebef73a704d897afa.hot-update.js",
    "/0.5d712f71e7d9abdbc976.hot-update.js": "/0.5d712f71e7d9abdbc976.hot-update.js",
    "/0.7ab7831e1e06d5b193ff.hot-update.js": "/0.7ab7831e1e06d5b193ff.hot-update.js",
    "/0.315997a9af5cf6600d58.hot-update.js": "/0.315997a9af5cf6600d58.hot-update.js",
    "/0.bc293b925cc15bc348b1.hot-update.js": "/0.bc293b925cc15bc348b1.hot-update.js",
    "/0.9300f41f2ab9786aa4c2.hot-update.js": "/0.9300f41f2ab9786aa4c2.hot-update.js",
    "/0.8aa7dd0a493468cdd2db.hot-update.js": "/0.8aa7dd0a493468cdd2db.hot-update.js",
    "/0.2734babe56bd0efc8ef9.hot-update.js": "/0.2734babe56bd0efc8ef9.hot-update.js",
    "/0.69297e2d3bdeba6ab87c.hot-update.js": "/0.69297e2d3bdeba6ab87c.hot-update.js",
    "/0.5d1d71655064240813e1.hot-update.js": "/0.5d1d71655064240813e1.hot-update.js",
    "/0.853cc3885a7ca336ab05.hot-update.js": "/0.853cc3885a7ca336ab05.hot-update.js",
    "/0.2b41385e3a25c2873c83.hot-update.js": "/0.2b41385e3a25c2873c83.hot-update.js",
    "/0.671d337b8a14468f6f48.hot-update.js": "/0.671d337b8a14468f6f48.hot-update.js",
    "/0.f77266fa06f87cd205e6.hot-update.js": "/0.f77266fa06f87cd205e6.hot-update.js",
    "/0.ee78bf1a94dbedea859c.hot-update.js": "/0.ee78bf1a94dbedea859c.hot-update.js",
    "/0.56785befe79ae5197dfc.hot-update.js": "/0.56785befe79ae5197dfc.hot-update.js",
    "/0.b992f1d973894da0add6.hot-update.js": "/0.b992f1d973894da0add6.hot-update.js",
    "/0.7f6d32997d8e161cf287.hot-update.js": "/0.7f6d32997d8e161cf287.hot-update.js",
    "/0.9c99b4bcce83f02ff786.hot-update.js": "/0.9c99b4bcce83f02ff786.hot-update.js",
    "/0.a8c9e04f7a078e9d0cd4.hot-update.js": "/0.a8c9e04f7a078e9d0cd4.hot-update.js",
    "/0.79132470c6119202d641.hot-update.js": "/0.79132470c6119202d641.hot-update.js",
    "/0.eee9a21f1bc0f70ad4e7.hot-update.js": "/0.eee9a21f1bc0f70ad4e7.hot-update.js",
    "/0.97c88afc073f1b60f7c5.hot-update.js": "/0.97c88afc073f1b60f7c5.hot-update.js",
    "/0.3842c142af56c9686645.hot-update.js": "/0.3842c142af56c9686645.hot-update.js",
    "/0.62ffa9c6fc0f15c2adeb.hot-update.js": "/0.62ffa9c6fc0f15c2adeb.hot-update.js",
    "/0.886c5e2f336c7e383b9e.hot-update.js": "/0.886c5e2f336c7e383b9e.hot-update.js",
    "/0.6651bd95699efb9d457a.hot-update.js": "/0.6651bd95699efb9d457a.hot-update.js",
    "/0.e4910ee39fb290a1ad7f.hot-update.js": "/0.e4910ee39fb290a1ad7f.hot-update.js",
    "/0.c26f89f8a4fd9e62ccd8.hot-update.js": "/0.c26f89f8a4fd9e62ccd8.hot-update.js",
    "/0.913acff2f4eeac8f3206.hot-update.js": "/0.913acff2f4eeac8f3206.hot-update.js",
    "/0.111382365e00d159cc03.hot-update.js": "/0.111382365e00d159cc03.hot-update.js",
    "/0.00a40633fcda5d75448c.hot-update.js": "/0.00a40633fcda5d75448c.hot-update.js",
    "/0.95c4fafed667867f1567.hot-update.js": "/0.95c4fafed667867f1567.hot-update.js",
    "/0.74311b3879d63992c81b.hot-update.js": "/0.74311b3879d63992c81b.hot-update.js",
    "/0.0c2d79958c554dd90a5a.hot-update.js": "/0.0c2d79958c554dd90a5a.hot-update.js",
    "/0.a5500bfd791455b80d74.hot-update.js": "/0.a5500bfd791455b80d74.hot-update.js",
    "/0.5c47e4c6c351eba94a99.hot-update.js": "/0.5c47e4c6c351eba94a99.hot-update.js",
    "/0.84fc3850816793b3d0ea.hot-update.js": "/0.84fc3850816793b3d0ea.hot-update.js",
    "/0.f7431873e8d96d7effc7.hot-update.js": "/0.f7431873e8d96d7effc7.hot-update.js",
    "/0.2ae414942b27f5243f64.hot-update.js": "/0.2ae414942b27f5243f64.hot-update.js",
    "/0.5af964d2de1db0051ae8.hot-update.js": "/0.5af964d2de1db0051ae8.hot-update.js",
    "/0.50bb8565fd46ffd2b1f3.hot-update.js": "/0.50bb8565fd46ffd2b1f3.hot-update.js",
    "/0.0381232f0ab5d5c945a1.hot-update.js": "/0.0381232f0ab5d5c945a1.hot-update.js",
    "/0.42fd125387d83a22e269.hot-update.js": "/0.42fd125387d83a22e269.hot-update.js",
    "/0.0353485a3b89e772d284.hot-update.js": "/0.0353485a3b89e772d284.hot-update.js",
    "/0.c7886c1413d4d6d7e382.hot-update.js": "/0.c7886c1413d4d6d7e382.hot-update.js",
    "/0.84eea2cc5ef574833c38.hot-update.js": "/0.84eea2cc5ef574833c38.hot-update.js",
    "/0.0800f6b250949e58eccf.hot-update.js": "/0.0800f6b250949e58eccf.hot-update.js",
    "/0.9ada809d96fcd0156415.hot-update.js": "/0.9ada809d96fcd0156415.hot-update.js",
    "/0.4c44e46b0de4d6250223.hot-update.js": "/0.4c44e46b0de4d6250223.hot-update.js",
    "/0.743ed19626d37036a2fa.hot-update.js": "/0.743ed19626d37036a2fa.hot-update.js",
    "/0.d96f051af1a6eb2e10f9.hot-update.js": "/0.d96f051af1a6eb2e10f9.hot-update.js",
    "/0.27a244ff7387a4e1542d.hot-update.js": "/0.27a244ff7387a4e1542d.hot-update.js",
    "/0.e16e8781b21a01ea5560.hot-update.js": "/0.e16e8781b21a01ea5560.hot-update.js",
    "/0.623cd114b27030214640.hot-update.js": "/0.623cd114b27030214640.hot-update.js",
    "/0.ca80db097b5c7c566bea.hot-update.js": "/0.ca80db097b5c7c566bea.hot-update.js",
    "/0.4f4e193665e3a001236c.hot-update.js": "/0.4f4e193665e3a001236c.hot-update.js",
    "/0.adb5b975f37d15991307.hot-update.js": "/0.adb5b975f37d15991307.hot-update.js",
    "/0.b77d768561f88eef8047.hot-update.js": "/0.b77d768561f88eef8047.hot-update.js",
    "/0.5cce94cd4bf032455007.hot-update.js": "/0.5cce94cd4bf032455007.hot-update.js",
    "/0.90c2a5368c07fdafc53b.hot-update.js": "/0.90c2a5368c07fdafc53b.hot-update.js",
    "/0.c3347ed733ac2c06ea3a.hot-update.js": "/0.c3347ed733ac2c06ea3a.hot-update.js",
    "/0.e2396f2478f195b03122.hot-update.js": "/0.e2396f2478f195b03122.hot-update.js",
    "/0.7392b7ff96cb4279649a.hot-update.js": "/0.7392b7ff96cb4279649a.hot-update.js",
    "/0.ec63b5ba0bc231841537.hot-update.js": "/0.ec63b5ba0bc231841537.hot-update.js",
    "/0.6c0d4254a427788bee9b.hot-update.js": "/0.6c0d4254a427788bee9b.hot-update.js",
    "/0.ce94f5cc9240044d3da9.hot-update.js": "/0.ce94f5cc9240044d3da9.hot-update.js",
    "/0.f27a7ee4989a04238e4a.hot-update.js": "/0.f27a7ee4989a04238e4a.hot-update.js",
    "/0.4b5271ff7a99b32400d7.hot-update.js": "/0.4b5271ff7a99b32400d7.hot-update.js",
    "/0.454a8814d51f016d87a4.hot-update.js": "/0.454a8814d51f016d87a4.hot-update.js",
    "/0.a5e835c895a106fb7b99.hot-update.js": "/0.a5e835c895a106fb7b99.hot-update.js",
    "/0.ecb0504c65eba48882a8.hot-update.js": "/0.ecb0504c65eba48882a8.hot-update.js",
    "/0.54e0a2bdc1dd0e180635.hot-update.js": "/0.54e0a2bdc1dd0e180635.hot-update.js",
    "/0.4cb5d50ec382cc58abf1.hot-update.js": "/0.4cb5d50ec382cc58abf1.hot-update.js",
    "/0.d5934907736ec16c69a4.hot-update.js": "/0.d5934907736ec16c69a4.hot-update.js",
    "/0.a0a7aeed8a152c09d08c.hot-update.js": "/0.a0a7aeed8a152c09d08c.hot-update.js",
    "/0.0b38296fd4d258057a4c.hot-update.js": "/0.0b38296fd4d258057a4c.hot-update.js",
    "/0.ded4ad62f834fa4b425f.hot-update.js": "/0.ded4ad62f834fa4b425f.hot-update.js",
    "/0.7017a31cc1fa4165b975.hot-update.js": "/0.7017a31cc1fa4165b975.hot-update.js",
    "/0.bd37cc1f128d124b7e36.hot-update.js": "/0.bd37cc1f128d124b7e36.hot-update.js",
    "/0.fe7a6eded1915dd41ad5.hot-update.js": "/0.fe7a6eded1915dd41ad5.hot-update.js",
    "/0.407e1c6767d09cd02f7e.hot-update.js": "/0.407e1c6767d09cd02f7e.hot-update.js",
    "/0.d23ff8c43d6181d54090.hot-update.js": "/0.d23ff8c43d6181d54090.hot-update.js",
    "/0.4b9fd712392d00e7dcec.hot-update.js": "/0.4b9fd712392d00e7dcec.hot-update.js",
    "/0.e8e1d832f2126269c0c6.hot-update.js": "/0.e8e1d832f2126269c0c6.hot-update.js",
    "/0.160f4c46599348adc97a.hot-update.js": "/0.160f4c46599348adc97a.hot-update.js",
    "/0.04498bcad5b7df997570.hot-update.js": "/0.04498bcad5b7df997570.hot-update.js",
    "/0.79f03f0c7e35296551e3.hot-update.js": "/0.79f03f0c7e35296551e3.hot-update.js",
    "/0.1c66441cac102bc60726.hot-update.js": "/0.1c66441cac102bc60726.hot-update.js",
    "/0.fae1fd82d7194a46a902.hot-update.js": "/0.fae1fd82d7194a46a902.hot-update.js",
    "/0.7aab339f382d09269eae.hot-update.js": "/0.7aab339f382d09269eae.hot-update.js",
    "/0.1f291a7b1c15a9d81c69.hot-update.js": "/0.1f291a7b1c15a9d81c69.hot-update.js",
    "/0.f59a9a4768765fec3acb.hot-update.js": "/0.f59a9a4768765fec3acb.hot-update.js",
    "/0.61ac996d10e7664a6a4b.hot-update.js": "/0.61ac996d10e7664a6a4b.hot-update.js",
    "/0.63941858c687c0a15bb5.hot-update.js": "/0.63941858c687c0a15bb5.hot-update.js",
    "/0.278ca2276a6b74c350d4.hot-update.js": "/0.278ca2276a6b74c350d4.hot-update.js",
    "/0.102098dd96f9e6081895.hot-update.js": "/0.102098dd96f9e6081895.hot-update.js",
    "/0.71e6e1087ce14d776cc9.hot-update.js": "/0.71e6e1087ce14d776cc9.hot-update.js",
    "/0.0724811d7ebfecbafede.hot-update.js": "/0.0724811d7ebfecbafede.hot-update.js",
    "/0.8e7b4c71fd0f851ccd22.hot-update.js": "/0.8e7b4c71fd0f851ccd22.hot-update.js",
    "/0.d5b16212a113ae496484.hot-update.js": "/0.d5b16212a113ae496484.hot-update.js",
    "/0.ca844cf0b4adc84a3097.hot-update.js": "/0.ca844cf0b4adc84a3097.hot-update.js",
    "/0.9b0ef5b4dabdb273ce41.hot-update.js": "/0.9b0ef5b4dabdb273ce41.hot-update.js",
    "/0.4137e7e2b17fdd136cad.hot-update.js": "/0.4137e7e2b17fdd136cad.hot-update.js",
    "/0.38e1ec866980cb776976.hot-update.js": "/0.38e1ec866980cb776976.hot-update.js",
    "/0.003936c8d90b7743f952.hot-update.js": "/0.003936c8d90b7743f952.hot-update.js",
    "/0.ffb9169a817b310301a7.hot-update.js": "/0.ffb9169a817b310301a7.hot-update.js",
    "/0.76ae1148b754c74821f1.hot-update.js": "/0.76ae1148b754c74821f1.hot-update.js",
    "/0.6480816b14de0f1902b0.hot-update.js": "/0.6480816b14de0f1902b0.hot-update.js",
    "/0.c37c08b5fe684b1bf38a.hot-update.js": "/0.c37c08b5fe684b1bf38a.hot-update.js",
    "/0.eddafe6ab251878f4d5a.hot-update.js": "/0.eddafe6ab251878f4d5a.hot-update.js",
    "/0.c519bab7ea1976f06675.hot-update.js": "/0.c519bab7ea1976f06675.hot-update.js",
    "/0.f28ac8173a9dba7b1ab5.hot-update.js": "/0.f28ac8173a9dba7b1ab5.hot-update.js",
    "/0.9606e6765cd90124e029.hot-update.js": "/0.9606e6765cd90124e029.hot-update.js",
    "/0.2f532db7ad67ff8c0ddb.hot-update.js": "/0.2f532db7ad67ff8c0ddb.hot-update.js",
    "/0.18cf023b5ff3d6657d1a.hot-update.js": "/0.18cf023b5ff3d6657d1a.hot-update.js",
    "/0.e0fca84216692f36cdc4.hot-update.js": "/0.e0fca84216692f36cdc4.hot-update.js",
    "/0.7a17afc8115f1e6531ab.hot-update.js": "/0.7a17afc8115f1e6531ab.hot-update.js",
    "/0.b3a9f88d603e93345060.hot-update.js": "/0.b3a9f88d603e93345060.hot-update.js",
    "/0.24be478b22fb542abb41.hot-update.js": "/0.24be478b22fb542abb41.hot-update.js",
    "/0.76c75cf4d1d5c4c53cca.hot-update.js": "/0.76c75cf4d1d5c4c53cca.hot-update.js",
    "/0.9d5e83d81ca4603ef270.hot-update.js": "/0.9d5e83d81ca4603ef270.hot-update.js",
    "/0.c0fca7f5dda2cfa2cf85.hot-update.js": "/0.c0fca7f5dda2cfa2cf85.hot-update.js",
    "/0.866a33e361f2daeedb7f.hot-update.js": "/0.866a33e361f2daeedb7f.hot-update.js",
    "/0.4f55ac3d54bda1ff831a.hot-update.js": "/0.4f55ac3d54bda1ff831a.hot-update.js",
    "/0.a43bab14a7ea9522ddad.hot-update.js": "/0.a43bab14a7ea9522ddad.hot-update.js",
    "/0.a9e000d7001934f5385c.hot-update.js": "/0.a9e000d7001934f5385c.hot-update.js",
    "/0.25c92b8db4128d7f1b53.hot-update.js": "/0.25c92b8db4128d7f1b53.hot-update.js",
    "/0.69a942abc9f1ba10748e.hot-update.js": "/0.69a942abc9f1ba10748e.hot-update.js",
    "/0.c95e9c7dd2655b2081d4.hot-update.js": "/0.c95e9c7dd2655b2081d4.hot-update.js",
    "/0.84d36784bbf9613e7325.hot-update.js": "/0.84d36784bbf9613e7325.hot-update.js",
    "/0.c33d9846f86bc8c89bc9.hot-update.js": "/0.c33d9846f86bc8c89bc9.hot-update.js",
    "/0.0ccdfef64f9e7f023371.hot-update.js": "/0.0ccdfef64f9e7f023371.hot-update.js",
    "/0.5a15e6674b332c60caa6.hot-update.js": "/0.5a15e6674b332c60caa6.hot-update.js",
    "/0.fb408d592dc477efa019.hot-update.js": "/0.fb408d592dc477efa019.hot-update.js",
    "/0.347690c8412638f9a95f.hot-update.js": "/0.347690c8412638f9a95f.hot-update.js",
    "/0.bddf21b1601f7079842c.hot-update.js": "/0.bddf21b1601f7079842c.hot-update.js",
    "/0.48b354cae77bcd1c14f6.hot-update.js": "/0.48b354cae77bcd1c14f6.hot-update.js",
    "/0.5b377211961f77eea6fe.hot-update.js": "/0.5b377211961f77eea6fe.hot-update.js",
    "/0.23ea79b58616ef3dbcc4.hot-update.js": "/0.23ea79b58616ef3dbcc4.hot-update.js",
    "/0.35f26c7acd000b16577e.hot-update.js": "/0.35f26c7acd000b16577e.hot-update.js",
    "/0.9fc81e094c066c72a23d.hot-update.js": "/0.9fc81e094c066c72a23d.hot-update.js",
    "/0.a815651a98805120a2f9.hot-update.js": "/0.a815651a98805120a2f9.hot-update.js",
    "/0.53ae253a4e3b7a8776d5.hot-update.js": "/0.53ae253a4e3b7a8776d5.hot-update.js",
    "/0.bedd6430c58ada4308d6.hot-update.js": "/0.bedd6430c58ada4308d6.hot-update.js",
    "/0.e724ad5727d99c7cf305.hot-update.js": "/0.e724ad5727d99c7cf305.hot-update.js",
    "/0.b3da0dcedc6f1c84ddfb.hot-update.js": "/0.b3da0dcedc6f1c84ddfb.hot-update.js",
    "/0.06dbb545ece18febef00.hot-update.js": "/0.06dbb545ece18febef00.hot-update.js",
    "/0.40da0373468d45f9246b.hot-update.js": "/0.40da0373468d45f9246b.hot-update.js",
    "/0.f24586913e310ebe88c4.hot-update.js": "/0.f24586913e310ebe88c4.hot-update.js",
    "/0.6cc232e827d8a11c58c3.hot-update.js": "/0.6cc232e827d8a11c58c3.hot-update.js",
    "/0.12304ab57c1d69947651.hot-update.js": "/0.12304ab57c1d69947651.hot-update.js"
}